{
  "input": "C:\\Users\\Admin\\Desktop\\Project\\DataXTown\\pixel-art\\zodiac-pets-economy\\transparent\\tiger.png",
  "name": "tiger",
  "out_dir": "C:\\Users\\Admin\\Desktop\\Project\\DataXTown\\pixel-art\\zodiac-pets-economy\\transparent\\tiger_pipe",
  "true_size": [
    251,
    251
  ],
  "detected_scale": 5,
  "import_method": "block",
  "strip_checker": false,
  "palette": null,
  "max_colors": 12,
  "before": {
    "colors": 5147,
    "semi_alpha_px": 0
  },
  "after": {
    "colors": 12,
    "semi_alpha_px": 0
  }
}